pyspedas_examples/__init__.py
pyspedas_examples/version.py
pyspedas_examples/examples/__init__.py
pyspedas_examples/examples/ex_analysis.py
pyspedas_examples/examples/ex_avg.py
pyspedas_examples/examples/ex_basic.py
pyspedas_examples/examples/ex_cdagui.py
pyspedas_examples/examples/ex_cdasws.py
pyspedas_examples/examples/ex_colors.py
pyspedas_examples/examples/ex_cotrans.py
pyspedas_examples/examples/ex_deriv.py
pyspedas_examples/examples/ex_dsl2gse.py
pyspedas_examples/examples/ex_gmag.py
pyspedas_examples/examples/ex_mpause_2.py
pyspedas_examples/examples/ex_mpause_t96.py
pyspedas_examples/examples/ex_smooth.py
pyspedas_examples/examples/ex_spectra.py
pyspedas_examples/examples/ex_spikes.py
pyspedas_examples/examples/ex_wavelet.py
pyspedas_examples-0.4.0.dist-info/LICENSE
pyspedas_examples-0.4.0.dist-info/METADATA
pyspedas_examples-0.4.0.dist-info/WHEEL
pyspedas_examples-0.4.0.dist-info/top_level.txt
pyspedas_examples-0.4.0.dist-info/RECORD
