Metadata-Version: 2.1
Name: pyspedas_examples
Version: 0.4.0
Summary: Examples of pySPEDAS
Home-page: https://github.com/spedas/pyspedas_examples
Author: Jim Lewis
Author-email: jwl@ssl.berkeley.edu
License: MIT
Project-URL: Information, http://spedas.org/wiki/
Keywords: examples spedas data tools
Classifier: Development Status :: 4 - Beta
Classifier: Intended Audience :: Science/Research
Classifier: Topic :: Scientific/Engineering
Classifier: License :: OSI Approved :: MIT License
Classifier: Programming Language :: Python :: 3
Requires-Python: >=3.8
License-File: LICENSE
Requires-Dist: pyspedas >=1.5.1
